metaminer/__init__.py
metaminer/__main__.py
metaminer/cli.py
metaminer/config.py
metaminer/datatype_inferrer.py
metaminer/document_reader.py
metaminer/extractor.py
metaminer/inquiry.py
metaminer/question_parser.py
metaminer/schema_builder.py
metaminer-0.3.6.dist-info/licenses/LICENSE
metaminer-0.3.6.dist-info/METADATA
metaminer-0.3.6.dist-info/WHEEL
metaminer-0.3.6.dist-info/entry_points.txt
metaminer-0.3.6.dist-info/top_level.txt
metaminer-0.3.6.dist-info/RECORD
