Metadata-Version: 2.4
Name: metaminer
Version: 0.3.6
Summary: Extract structured information from documents using AI
Author-email: Travis Adams <tadams792@gmail.com>
Maintainer-email: Travis Adams <tadams792@gmail.com>
License:                    GNU LESSER GENERAL PUBLIC LICENSE
Project-URL: Homepage, https://github.com/travis4dams/metaminer
Project-URL: Repository, https://github.com/travis4dams/metaminer
Project-URL: Issues, https://github.com/travis4dams/metaminer/issues
Project-URL: PyPI, https://pypi.org/project/metaminer/
Project-URL: Documentation, https://github.com/travis4dams/metaminer#readme
Keywords: ai,document,extraction,nlp,openai,structured-data
Classifier: Development Status :: 3 - Alpha
Classifier: Intended Audience :: Developers
Classifier: Operating System :: OS Independent
Classifier: Programming Language :: Python :: 3
Classifier: Programming Language :: Python :: 3.8
Classifier: Programming Language :: Python :: 3.9
Classifier: Programming Language :: Python :: 3.10
Classifier: Programming Language :: Python :: 3.11
Classifier: Programming Language :: Python :: 3.12
Classifier: Topic :: Scientific/Engineering :: Artificial Intelligence
Classifier: Topic :: Text Processing :: General
Classifier: Topic :: Software Development :: Libraries :: Python Modules
Requires-Python: >=3.8
License-File: LICENSE
Requires-Dist: openai>=1.0.0
Requires-Dist: pandas>=1.3.0
Requires-Dist: pydantic>=2.0.0
Requires-Dist: pypandoc>=1.5
Requires-Dist: PyMuPDF>=1.20.0
Requires-Dist: python-dateutil>=2.8.0
Requires-Dist: typing_extensions>=4.0.0; python_version < "3.9"
Provides-Extra: dev
Requires-Dist: pytest>=6.0; extra == "dev"
Requires-Dist: pytest-mock; extra == "dev"
Dynamic: license-file
